[
    {
        "name":"Buddha Statue",
        "price":2500,
        "description":"The sitting Buddha is the most common representation of the Buddha. These Buddha statues can represent teaching, meditation, or an attempt to reach enlightenment.",
        "rating":4.8,
        "images":[
            {"public_id":"statue",
                "url":"https://images.unsplash.com/photo-1537903904737-13fc83b81be0?ixlib=rb-1.2.1&ixid=MXwxMjA3fDB8MHxwaG90by1wYWdlfHx8fGVufDB8fHw%3D&auto=format&fit=crop&w=750&q=80"
            },
            {
                "public_id": "statue",
                "url": "https://images.unsplash.com/photo-1597469713172-318cae054a5e?ixid=MXwxMjA3fDB8MHxwaG90by1wYWdlfHx8fGVufDB8fHw%3D&ixlib=rb-1.2.1&auto=format&fit=crop&w=750&q=80"
            }
        ],
        "category":"Food",
        "seller":"Amazon",
        "stock":200,
        "numOfReviews":56,
        "reviews":[]
    },
    {
        "name": "Buddha Statue",
        "price": 2500,
        "description": "The sitting Buddha is the most common representation of the Buddha. These Buddha statues can represent teaching, meditation, or an attempt to reach enlightenment.",
        "rating": 4.8,
        "images": [
            {
                "public_id": "statue",
                "url": "https://images.unsplash.com/photo-1537903904737-13fc83b81be0?ixlib=rb-1.2.1&ixid=MXwxMjA3fDB8MHxwaG90by1wYWdlfHx8fGVufDB8fHw%3D&auto=format&fit=crop&w=750&q=80"
            },
            {
                "public_id": "statue",
                "url": "https://images.unsplash.com/photo-1597469713172-318cae054a5e?ixid=MXwxMjA3fDB8MHxwaG90by1wYWdlfHx8fGVufDB8fHw%3D&ixlib=rb-1.2.1&auto=format&fit=crop&w=750&q=80"
            }
        ],
        "category": "Food",
        "seller": "Amazon",
        "stock": 200,
        "numOfReviews": 56,
        "reviews": []
    },
    {
        "name": "Buddha Statue",
        "price": 2500,
        "description": "The sitting Buddha is the most common representation of the Buddha. These Buddha statues can represent teaching, meditation, or an attempt to reach enlightenment.",
        "rating": 4.8,
        "images": [
            {
                "public_id": "statue",
                "url": "https://images.unsplash.com/photo-1537903904737-13fc83b81be0?ixlib=rb-1.2.1&ixid=MXwxMjA3fDB8MHxwaG90by1wYWdlfHx8fGVufDB8fHw%3D&auto=format&fit=crop&w=750&q=80"
            },
            {
                "public_id": "statue",
                "url": "https://images.unsplash.com/photo-1597469713172-318cae054a5e?ixid=MXwxMjA3fDB8MHxwaG90by1wYWdlfHx8fGVufDB8fHw%3D&ixlib=rb-1.2.1&auto=format&fit=crop&w=750&q=80"
            }
        ],
        "category": "Food",
        "seller": "Amazon",
        "stock": 200,
        "numOfReviews": 56,
        "reviews": []
    },
    {
        "name": "Buddha Statue",
        "price": 2500,
        "description": "The sitting Buddha is the most common representation of the Buddha. These Buddha statues can represent teaching, meditation, or an attempt to reach enlightenment.",
        "rating": 4.8,
        "images": [
            {
                "public_id": "statue",
                "url": "https://images.unsplash.com/photo-1537903904737-13fc83b81be0?ixlib=rb-1.2.1&ixid=MXwxMjA3fDB8MHxwaG90by1wYWdlfHx8fGVufDB8fHw%3D&auto=format&fit=crop&w=750&q=80"
            },
            {
                "public_id": "statue",
                "url": "https://images.unsplash.com/photo-1597469713172-318cae054a5e?ixid=MXwxMjA3fDB8MHxwaG90by1wYWdlfHx8fGVufDB8fHw%3D&ixlib=rb-1.2.1&auto=format&fit=crop&w=750&q=80"
            }
        ],
        "category": "Food",
        "seller": "Amazon",
        "stock": 200,
        "numOfReviews": 56,
        "reviews": []
    },
    {
        "name": "Buddha Statue",
        "price": 2500,
        "description": "The sitting Buddha is the most common representation of the Buddha. These Buddha statues can represent teaching, meditation, or an attempt to reach enlightenment.",
        "rating": 4.8,
        "images": [
            {
                "public_id": "statue",
                "url": "https://images.unsplash.com/photo-1537903904737-13fc83b81be0?ixlib=rb-1.2.1&ixid=MXwxMjA3fDB8MHxwaG90by1wYWdlfHx8fGVufDB8fHw%3D&auto=format&fit=crop&w=750&q=80"
            },
            {
                "public_id": "statue",
                "url": "https://images.unsplash.com/photo-1597469713172-318cae054a5e?ixid=MXwxMjA3fDB8MHxwaG90by1wYWdlfHx8fGVufDB8fHw%3D&ixlib=rb-1.2.1&auto=format&fit=crop&w=750&q=80"
            }
        ],
        "category": "Food",
        "seller": "Amazon",
        "stock": 200,
        "numOfReviews": 56,
        "reviews": []
    },
    {
        "name": "Buddha Statue",
        "price": 2500,
        "description": "The sitting Buddha is the most common representation of the Buddha. These Buddha statues can represent teaching, meditation, or an attempt to reach enlightenment.",
        "rating": 4.8,
        "images": [
            {
                "public_id": "statue",
                "url": "https://images.unsplash.com/photo-1537903904737-13fc83b81be0?ixlib=rb-1.2.1&ixid=MXwxMjA3fDB8MHxwaG90by1wYWdlfHx8fGVufDB8fHw%3D&auto=format&fit=crop&w=750&q=80"
            },
            {
                "public_id": "statue",
                "url": "https://images.unsplash.com/photo-1597469713172-318cae054a5e?ixid=MXwxMjA3fDB8MHxwaG90by1wYWdlfHx8fGVufDB8fHw%3D&ixlib=rb-1.2.1&auto=format&fit=crop&w=750&q=80"
            }
        ],
        "category": "Food",
        "seller": "Amazon",
        "stock": 200,
        "numOfReviews": 56,
        "reviews": []
    },
    {
        "name": "Buddha Statue",
        "price": 2500,
        "description": "The sitting Buddha is the most common representation of the Buddha. These Buddha statues can represent teaching, meditation, or an attempt to reach enlightenment.",
        "rating": 4.8,
        "images": [
            {
                "public_id": "statue",
                "url": "https://images.unsplash.com/photo-1537903904737-13fc83b81be0?ixlib=rb-1.2.1&ixid=MXwxMjA3fDB8MHxwaG90by1wYWdlfHx8fGVufDB8fHw%3D&auto=format&fit=crop&w=750&q=80"
            },
            {
                "public_id": "statue",
                "url": "https://images.unsplash.com/photo-1597469713172-318cae054a5e?ixid=MXwxMjA3fDB8MHxwaG90by1wYWdlfHx8fGVufDB8fHw%3D&ixlib=rb-1.2.1&auto=format&fit=crop&w=750&q=80"
            }
        ],
        "category": "Food",
        "seller": "Amazon",
        "stock": 200,
        "numOfReviews": 56,
        "reviews": []
    },
    {
        "name": "Buddha Statue",
        "price": 2500,
        "description": "The sitting Buddha is the most common representation of the Buddha. These Buddha statues can represent teaching, meditation, or an attempt to reach enlightenment.",
        "rating": 4.8,
        "images": [
            {
                "public_id": "statue",
                "url": "https://images.unsplash.com/photo-1537903904737-13fc83b81be0?ixlib=rb-1.2.1&ixid=MXwxMjA3fDB8MHxwaG90by1wYWdlfHx8fGVufDB8fHw%3D&auto=format&fit=crop&w=750&q=80"
            },
            {
                "public_id": "statue",
                "url": "https://images.unsplash.com/photo-1597469713172-318cae054a5e?ixid=MXwxMjA3fDB8MHxwaG90by1wYWdlfHx8fGVufDB8fHw%3D&ixlib=rb-1.2.1&auto=format&fit=crop&w=750&q=80"
            }
        ],
        "category": "Food",
        "seller": "Amazon",
        "stock": 200,
        "numOfReviews": 56,
        "reviews": []
    },
    {
        "name": "Buddha Statue",
        "price": 2500,
        "description": "The sitting Buddha is the most common representation of the Buddha. These Buddha statues can represent teaching, meditation, or an attempt to reach enlightenment.",
        "rating": 4.8,
        "images": [
            {
                "public_id": "statue",
                "url": "https://images.unsplash.com/photo-1537903904737-13fc83b81be0?ixlib=rb-1.2.1&ixid=MXwxMjA3fDB8MHxwaG90by1wYWdlfHx8fGVufDB8fHw%3D&auto=format&fit=crop&w=750&q=80"
            },
            {
                "public_id": "statue",
                "url": "https://images.unsplash.com/photo-1597469713172-318cae054a5e?ixid=MXwxMjA3fDB8MHxwaG90by1wYWdlfHx8fGVufDB8fHw%3D&ixlib=rb-1.2.1&auto=format&fit=crop&w=750&q=80"
            }
        ],
        "category": "Food",
        "seller": "Amazon",
        "stock": 200,
        "numOfReviews": 56,
        "reviews": []
    },
    {
        "name": "Buddha Statue",
        "price": 2500,
        "description": "The sitting Buddha is the most common representation of the Buddha. These Buddha statues can represent teaching, meditation, or an attempt to reach enlightenment.",
        "rating": 4.8,
        "images": [
            {
                "public_id": "statue",
                "url": "https://images.unsplash.com/photo-1537903904737-13fc83b81be0?ixlib=rb-1.2.1&ixid=MXwxMjA3fDB8MHxwaG90by1wYWdlfHx8fGVufDB8fHw%3D&auto=format&fit=crop&w=750&q=80"
            },
            {
                "public_id": "statue",
                "url": "https://images.unsplash.com/photo-1597469713172-318cae054a5e?ixid=MXwxMjA3fDB8MHxwaG90by1wYWdlfHx8fGVufDB8fHw%3D&ixlib=rb-1.2.1&auto=format&fit=crop&w=750&q=80"
            }
        ],
        "category": "Food",
        "seller": "Amazon",
        "stock": 200,
        "numOfReviews": 56,
        "reviews": []
    },
    {
        "name": "Buddha Statue",
        "price": 2500,
        "description": "The sitting Buddha is the most common representation of the Buddha. These Buddha statues can represent teaching, meditation, or an attempt to reach enlightenment.",
        "rating": 4.8,
        "images": [
            {
                "public_id": "statue",
                "url": "https://images.unsplash.com/photo-1537903904737-13fc83b81be0?ixlib=rb-1.2.1&ixid=MXwxMjA3fDB8MHxwaG90by1wYWdlfHx8fGVufDB8fHw%3D&auto=format&fit=crop&w=750&q=80"
            },
            {
                "public_id": "statue",
                "url": "https://images.unsplash.com/photo-1597469713172-318cae054a5e?ixid=MXwxMjA3fDB8MHxwaG90by1wYWdlfHx8fGVufDB8fHw%3D&ixlib=rb-1.2.1&auto=format&fit=crop&w=750&q=80"
            }
        ],
        "category": "Food",
        "seller": "Amazon",
        "stock": 200,
        "numOfReviews": 56,
        "reviews": []
    },
    {
        "name": "Buddha Statue",
        "price": 2500,
        "description": "The sitting Buddha is the most common representation of the Buddha. These Buddha statues can represent teaching, meditation, or an attempt to reach enlightenment.",
        "rating": 4.8,
        "images": [
            {
                "public_id": "statue",
                "url": "https://images.unsplash.com/photo-1537903904737-13fc83b81be0?ixlib=rb-1.2.1&ixid=MXwxMjA3fDB8MHxwaG90by1wYWdlfHx8fGVufDB8fHw%3D&auto=format&fit=crop&w=750&q=80"
            },
            {
                "public_id": "statue",
                "url": "https://images.unsplash.com/photo-1597469713172-318cae054a5e?ixid=MXwxMjA3fDB8MHxwaG90by1wYWdlfHx8fGVufDB8fHw%3D&ixlib=rb-1.2.1&auto=format&fit=crop&w=750&q=80"
            }
        ],
        "category": "Food",
        "seller": "Amazon",
        "stock": 200,
        "numOfReviews": 56,
        "reviews": []
    },
    {
        "name": "Buddha Statue",
        "price": 2500,
        "description": "The sitting Buddha is the most common representation of the Buddha. These Buddha statues can represent teaching, meditation, or an attempt to reach enlightenment.",
        "rating": 4.8,
        "images": [
            {
                "public_id": "statue",
                "url": "https://images.unsplash.com/photo-1537903904737-13fc83b81be0?ixlib=rb-1.2.1&ixid=MXwxMjA3fDB8MHxwaG90by1wYWdlfHx8fGVufDB8fHw%3D&auto=format&fit=crop&w=750&q=80"
            },
            {
                "public_id": "statue",
                "url": "https://images.unsplash.com/photo-1597469713172-318cae054a5e?ixid=MXwxMjA3fDB8MHxwaG90by1wYWdlfHx8fGVufDB8fHw%3D&ixlib=rb-1.2.1&auto=format&fit=crop&w=750&q=80"
            }
        ],
        "category": "Food",
        "seller": "Amazon",
        "stock": 200,
        "numOfReviews": 56,
        "reviews": []
    },
    {
        "name": "Buddha Statue",
        "price": 2500,
        "description": "The sitting Buddha is the most common representation of the Buddha. These Buddha statues can represent teaching, meditation, or an attempt to reach enlightenment.",
        "rating": 4.8,
        "images": [
            {
                "public_id": "statue",
                "url": "https://images.unsplash.com/photo-1537903904737-13fc83b81be0?ixlib=rb-1.2.1&ixid=MXwxMjA3fDB8MHxwaG90by1wYWdlfHx8fGVufDB8fHw%3D&auto=format&fit=crop&w=750&q=80"
            },
            {
                "public_id": "statue",
                "url": "https://images.unsplash.com/photo-1597469713172-318cae054a5e?ixid=MXwxMjA3fDB8MHxwaG90by1wYWdlfHx8fGVufDB8fHw%3D&ixlib=rb-1.2.1&auto=format&fit=crop&w=750&q=80"
            }
        ],
        "category": "Food",
        "seller": "Amazon",
        "stock": 200,
        "numOfReviews": 56,
        "reviews": []
    },
    {
        "name": "Buddha Statue",
        "price": 2500,
        "description": "The sitting Buddha is the most common representation of the Buddha. These Buddha statues can represent teaching, meditation, or an attempt to reach enlightenment.",
        "rating": 4.8,
        "images": [
            {
                "public_id": "statue",
                "url": "https://images.unsplash.com/photo-1537903904737-13fc83b81be0?ixlib=rb-1.2.1&ixid=MXwxMjA3fDB8MHxwaG90by1wYWdlfHx8fGVufDB8fHw%3D&auto=format&fit=crop&w=750&q=80"
            },
            {
                "public_id": "statue",
                "url": "https://images.unsplash.com/photo-1597469713172-318cae054a5e?ixid=MXwxMjA3fDB8MHxwaG90by1wYWdlfHx8fGVufDB8fHw%3D&ixlib=rb-1.2.1&auto=format&fit=crop&w=750&q=80"
            }
        ],
        "category": "Food",
        "seller": "Amazon",
        "stock": 200,
        "numOfReviews": 56,
        "reviews": []
    }

]